[{"_index":"filebeat-6.4.2-2018.12.24","_type":"doc","_id":"-zcR4mcByf0ZFSOWENc2","_score":1,"_source":{"@timestamp":"2018-12-24T21:13:46.886Z","prospector":{"type":"docker"},"beat":{"name":"9ec4fbd6e673","hostname":"9ec4fbd6e673","version":"6.4.2"},"host":{"name":"9ec4fbd6e673"},"source":"/var/lib/docker/containers/9ec4fbd6e673a1df41278b3553bea63ef76250c718583a4ddba6a5c922ea94ae/9ec4fbd6e673a1df41278b3553bea63ef76250c718583a4ddba6a5c922ea94ae-json.log","offset":180962,"stream":"stderr","message":"time=\"Dec 24 09:13:46.886\" level=info msg=\"Generator Queue: 0 Output Queue: 0\" file=run.go func=run.ROT line=18 ","input":{"type":"docker"},"_raw":"{\"@timestamp\":\"2018-12-24T21:13:46.886Z\",\"prospector\":{\"type\":\"docker\"},\"beat\":{\"name\":\"9ec4fbd6e673\",\"hostname\":\"9ec4fbd6e673\",\"version\":\"6.4.2\"},\"host\":{\"name\":\"9ec4fbd6e673\"},\"source\":\"/var/lib/docker/containers/9ec4fbd6e673a1df41278b3553bea63ef76250c718583a4ddba6a5c922ea94ae/9ec4fbd6e673a1df41278b3553bea63ef76250c718583a4ddba6a5c922ea94ae-json.log\",\"offset\":180962,\"stream\":\"stderr\",\"message\":\"time=\\\"Dec 24 09:13:46.886\\\" level=info msg=\\\"Generator Queue: 0 Output Queue: 0\\\" file=run.go func=run.ROT line=18 \",\"input\":{\"type\":\"docker\"}}","cribl_pipe":"elastic"},"fields":{"@timestamp":["2018-12-24T21:13:46.886Z"]}}]